deflefpy/__init__.py
deflefpy/def_data.py
deflefpy/def_read.py
deflefpy/def_write.py
deflefpy/lef_data.py
deflefpy/lef_read.py
deflefpy/lef_write.py
deflefpy/util.py
deflefpy-0.1.3.dist-info/LICENSE
deflefpy-0.1.3.dist-info/WHEEL
deflefpy-0.1.3.dist-info/METADATA
deflefpy-0.1.3.dist-info/RECORD
